{"path":"home/work/machineLearning","templateID":2,"sharedPropsHashes":{},"localProps":{"note":{"path":"home/work/machineLearning","name":"Machine Learning","parent":"home/work","contents":"<p>I am currently enrolled in Andrew Ng&#39;s machine learning course on Coursera. </p>\n<h3 id=\"reasons\">Reasons</h3>\n<ul>\n<li>Learning more about the current state of AI will improve my ability to see through AI hype and understand the true future consequences of AI which I think will be significant.</li>\n<li>Learning how computers think will improve my ability to think.</li>\n<li>The course will help me to appreciate the technical details behind the challenge of keeping AI beneficial.</li>\n</ul>\n<p>Start date: January 2019</p>\n<p>Predicted end: May 2019</p>\n","folder":0},"children_notes":[]}}
